Workbook

Sheet Hoja1
A1: Factura | B1: Nombre | C1: Valor | D1: Fecha | E1: DESCUNTO
A2: GASTOS | B2: IVA | C2: 1088000 | D2: 46275 | E2: =VLOOKUP(B2,Hoja2!A:B,2,FALSE) -> OBLIGATORIO
A3: GASTOS | B3: RTE ICA | C3: 1404000 | D3: 46224 | E3: =VLOOKUP(B3,Hoja2!A:B,2,FALSE) -> OBLIGATORIO
A4: GASTOS | B4: Poliza de seguro PYME | C4: 2200000 | D4: 46203 | E4: =VLOOKUP(B4,Hoja2!A:B,2,FALSE) -> OBLIGATORIO
A5: GASTOS | B5: Honorarios Contabilidad ACT&J | C5: 2323000 | D5: 46188 | E5: =VLOOKUP(B5,Hoja2!A:B,2,FALSE) -> OBLIGATORIO
A6: GASTOS | B6: Comisiones Jeimy Paola Ortiz Duarte (JUL) | C6: 1895696.6 | D6: 46310 | E6: =VLOOKUP(B6,Hoja2!A:B,2,FALSE) -> MANEJABLE
A7: GASTOS | B7: Comisiones Nancy Rosalba Mora moreno Ventas (MAY) | C7: 2494617.2 | D7: 46127 | E7: =VLOOKUP(B7,Hoja2!A:B,2,FALSE) -> OBLIGATORIO
A8: GASTOS | B8: Comisiones Antonio Bernal Cardona (MAY) | C8: 3341480.9 | D8: 46188 | E8: =VLOOKUP(B8,Hoja2!A:B,2,FALSE) -> OBLIGATORIO
A9: GASTOS | B9: Comisiones Luz Stella Bernal Cardona (MAY) | C9: 796009.8 | D9: 46188 | E9: =VLOOKUP(B9,Hoja2!A:B,2,FALSE) -> OBLIGATORIO
A10: GASTOS | B10: Comisiones Luz Stella Bernal Cardona (ABR) | C10: 796009.8 | D10: 46157 | E10: =VLOOKUP(B10,Hoja2!A:B,2,FALSE) -> IMPORTANTE
A11: GASTOS | B11: Comisiones Saludia Santiago Feliciano (Ronald) | C11: 1605638 | D11: 46183 | E11: =VLOOKUP(B11,Hoja2!A:B,2,FALSE) -> IMPORTANTE
A12: GASTOS | B12: Pago de intereses préstamo de S&P marzo 2023 a diciembre 2024 | C12: 26832432 | D12: 45016 | E12: =VLOOKUP(B12,Hoja2!A:B,2,FALSE) -> IMPORTANTE
A13: GASTOS | B13: Intereses viejos (Obligatorio) | C13: 1770000 | D13: 46157 | E13: =VLOOKUP(B13,Hoja2!A:B,2,FALSE) -> OBLIGATORIO
... A126: PROVEDOR | B126: DEPOSITO DE DROGAS MONACO SAS | C126: 5129410 | D126: 46265 | E126: =VLOOKUP(B126,Hoja2!A:B,2,FALSE) -> IMPORTANTE

Sheet Hoja2
A1: ANTONIO BERNAL | B1: MANEJABLE
A2: 1° Prima de servicios | B2: OBLIGATORIO
A3: Acueducto Bodega | B3: OBLIGATORIO
A4: AIPHEX GLOBALPHARMA SAS | B4: IMPORTANTE
A5: AIPHEX GLOBAPHARMA SAS | B5: IMPORTANTE
A6: ALDANKEMI LTDA | B6: OBLIGATORIO
A7: ALFA TRADING SAS | B7: IMPORTANTE
A8: ANDRES SALOMON | B8: MANEJABLE
A9: Arriendo Bodega nueva | B9: OBLIGATORIO
A10: Arriendo Bodega nueva | B10: IMPORTANTE
A11: Arriendo Software Mantis | B11: OBLIGATORIO
A12: BIAL PHARMACEUTICAL | B12: MANEJABLE
... A224: VELMORE DISTRIBUCIONES SAS | B224: OBLIGATORIO
